[
  {
    "id": 1,
    "category_id": 1,
    "name": "Cà Phê Đen",
    "price": 15000,
    "status": "active",
    "options": [],
    "image": ""
  },
  {
    "id": 2,
    "category_id": 1,
    "name": "Cà Phê Sữa",
    "price": 20000,
    "status": "active",
    "options": [],
    "image": ""
  },
  {
    "id": 3,
    "category_id": 1,
    "name": "Trà Sữa Trân Châu",
    "price": 25000,
    "status": "active",
    "options": [],
    "image": ""
  },
  {
    "id": 4,
    "category_id": 2,
    "name": "Cá Viên Chiên",
    "price": 50000,
    "status": "active",
    "options": [],
    "image": ""
  }
]